.bumpversion.cfg
.git_archival.txt
.gitattributes
.gitchangelog.rc
.gitignore
CHANGELOG.md
CODE_OF_CONDUCT.md
LICENSE
README.md
RELEASING.md
TODO.rst
setup.cfg
setup.py
.github/ISSUE_TEMPLATE.md
.github/PULL_REQUEST_TEMPLATE.md
.github/workflows/ci.yaml
.github/workflows/deploy-sdist.yaml
bin/modis_dr_runner.py
bin/seadas_modis_runner.py
continuous_integration/environment.yaml
examples/modis_dr_config.yaml
examples/modis_dr_runner.sh_template
examples/modis_ingester.py
modis_runner/__init__.py
modis_runner/config.py
modis_runner/logger.py
modis_runner/publish_and_listen.py
modis_runner/utils.py
modis_runner/version.py
modis_runner.egg-info/PKG-INFO
modis_runner.egg-info/SOURCES.txt
modis_runner.egg-info/dependency_links.txt
modis_runner.egg-info/not-zip-safe
modis_runner.egg-info/requires.txt
modis_runner.egg-info/top_level.txt
modis_runner/tests/test_modis_runner.py
modis_runner/tests/test_utils.py